ltipinfo/__init__.py
ltipinfo/ltipinfo.py
ltipinfo-1.6.0.dist-info/LICENSE
ltipinfo-1.6.0.dist-info/METADATA
ltipinfo-1.6.0.dist-info/WHEEL
ltipinfo-1.6.0.dist-info/top_level.txt
ltipinfo-1.6.0.dist-info/RECORD
